md2term.py
md2term-1.0.2.dist-info/METADATA
md2term-1.0.2.dist-info/WHEEL
md2term-1.0.2.dist-info/entry_points.txt
md2term-1.0.2.dist-info/licenses/LICENSE
md2term-1.0.2.dist-info/RECORD
