Metadata-Version: 2.4
Name: md2term
Version: 1.0.2
Summary: Parse Markdown and turn it into nicely-formatted text for terminal display
Project-URL: Homepage, https://github.com/statico/md2term
Project-URL: Repository, https://github.com/statico/md2term
Project-URL: Issues, https://github.com/statico/md2term/issues
Project-URL: Changelog, https://github.com/statico/md2term/releases
Author-email: Ian Langworth ☠ <ian@langworth.com>
License: Apache-2.0
License-File: LICENSE
Keywords: cli,formatting,markdown,terminal
Classifier: Development Status :: 5 - Production/Stable
Classifier: Intended Audience :: Developers
Classifier: License :: OSI Approved :: Apache Software License
Classifier: Programming Language :: Python :: 3
Classifier: Programming Language :: Python :: 3.8
Classifier: Programming Language :: Python :: 3.9
Classifier: Programming Language :: Python :: 3.10
Classifier: Programming Language :: Python :: 3.11
Classifier: Programming Language :: Python :: 3.12
Classifier: Programming Language :: Python :: 3.13
Classifier: Topic :: Text Processing :: Markup
Classifier: Topic :: Utilities
Requires-Python: >=3.8.1
Requires-Dist: click>=8.0.0
Requires-Dist: markdown>=3.4.0
Requires-Dist: mistune>=3.1.3
Requires-Dist: rich-click>=1.8.9
Requires-Dist: rich>=13.0.0
Provides-Extra: dev
Requires-Dist: black>=23.0.0; extra == 'dev'
Requires-Dist: mypy>=1.0.0; extra == 'dev'
Requires-Dist: ruff>=0.1.0; extra == 'dev'
Provides-Extra: test
Requires-Dist: pytest-cov>=4.0.0; extra == 'test'
Requires-Dist: pytest>=7.0.0; extra == 'test'
Requires-Dist: syrupy>=4.0.0; extra == 'test'
